gisflu-0.1.10.dist-info/METADATA
gisflu-0.1.10.dist-info/WHEEL
gisflu-0.1.10.dist-info/entry_points.txt
gisflu/__init__.py
gisflu/browse.py
gisflu/credentials.py
gisflu/download.py
gisflu/login.py
gisflu/utils.py
gisflu-0.1.10.dist-info/RECORD
